multiclass_model/VERSION
multiclass_model/__init__.py
multiclass_model/config.yml
multiclass_model/pipeline.py
multiclass_model/predict.py
multiclass_model/train_pipeline.py
multiclass_model/config/__init__.py
multiclass_model/config/core.py
multiclass_model/custom_functions/__init__.py
multiclass_model/custom_functions/custom_functions.py
multiclass_model/datasets/__init__.py
multiclass_model/datasets/test.csv
multiclass_model/datasets/train.csv
multiclass_model/processing/__init__.py
multiclass_model/processing/data_manager.py
multiclass_model/processing/validation.py
multiclass_model/trained_models/__init__.py
multiclass_model/trained_models/multiclass_model_output_v0.1.0.pkl
tid_multiclass_model-0.1.0.dist-info/METADATA
tid_multiclass_model-0.1.0.dist-info/WHEEL
tid_multiclass_model-0.1.0.dist-info/top_level.txt
tid_multiclass_model-0.1.0.dist-info/RECORD
